LICENSE
MANIFEST.in
README.md
setup.cfg
setup.py
imagepy/IPy.py
imagepy/__init__.py
imagepy/__main__.py
imagepy.egg-info/PKG-INFO
imagepy.egg-info/SOURCES.txt
imagepy.egg-info/dependency_links.txt
imagepy.egg-info/entry_points.txt
imagepy.egg-info/requires.txt
imagepy.egg-info/top_level.txt
imagepy/core/__init__.py
imagepy/core/draw/__init__.py
imagepy/core/draw/fill.py
imagepy/core/draw/paint.py
imagepy/core/draw/polygonfill.py
imagepy/core/engine/__init__.py
imagepy/core/engine/filter.py
imagepy/core/engine/free.py
imagepy/core/engine/macros.py
imagepy/core/engine/mkdown.py
imagepy/core/engine/report.py
imagepy/core/engine/simple.py
imagepy/core/engine/table.py
imagepy/core/engine/tool.py
imagepy/core/engine/widget.py
imagepy/core/engine/workflow.py
imagepy/core/loader/__init__.py
imagepy/core/loader/loader.py
imagepy/core/manager/__init__.py
imagepy/core/manager/clipbdmanager.py
imagepy/core/manager/colormanager.py
imagepy/core/manager/configmanager.py
imagepy/core/manager/documentmanager.py
imagepy/core/manager/iomanager.py
imagepy/core/manager/languagemanager.py
imagepy/core/manager/pluginmanager.py
imagepy/core/manager/roimanager.py
imagepy/core/manager/shotcutmanager.py
imagepy/core/manager/taskmanager.py
imagepy/core/manager/windowmanager.py
imagepy/core/mark/__init__.py
imagepy/core/mark/mark.py
imagepy/core/myvi/__init__.py
imagepy/core/myvi/canvas3d.py
imagepy/core/myvi/frame3d.py
imagepy/core/myvi/manager.py
imagepy/core/myvi/txtmark.py
imagepy/core/myvi/util.py
imagepy/core/myvi/imgs/__init__.py
imagepy/core/myvi/imgs/configure.png
imagepy/core/myvi/imgs/isometric.png
imagepy/core/myvi/imgs/logo.ico
imagepy/core/myvi/imgs/open.png
imagepy/core/myvi/imgs/parallel.png
imagepy/core/myvi/imgs/save.png
imagepy/core/myvi/imgs/stl.png
imagepy/core/myvi/imgs/x-axis.png
imagepy/core/myvi/imgs/y-axis.png
imagepy/core/myvi/imgs/z-axis.png
imagepy/core/pixel/__init__.py
imagepy/core/pixel/bliter.py
imagepy/core/roi/__init__.py
imagepy/core/roi/convert.py
imagepy/core/roi/lineroi.py
imagepy/core/roi/ovalroi.py
imagepy/core/roi/pointroi.py
imagepy/core/roi/polygonroi.py
imagepy/core/roi/rectangleroi.py
imagepy/core/roi/roi.py
