Metadata-Version: 1.0
Name: imagepy
Version: 0.22
Summary: interactive python image-processing plugin framework
Home-page: https://github.com/Image-Py/imagepy
Author: YXDragon
Author-email: yxdragon@imagepy.org
License: BSD 3-clause
Platform: UNKNOWN
